latexclippings.py
latexclippings-0.1.3.dist-info/LICENSE.md
latexclippings-0.1.3.dist-info/METADATA
latexclippings-0.1.3.dist-info/WHEEL
latexclippings-0.1.3.dist-info/entry_points.txt
latexclippings-0.1.3.dist-info/top_level.txt
latexclippings-0.1.3.dist-info/RECORD
