Metadata-Version: 2.1
Name: latexclippings
Version: 0.1.3
Summary: Batch render LaTeX files to cropped SVG images
Home-page: https://github.com/justinyaodu/LaTeXclippings
Author: Justin Yao Du
Author-email: justinyaodu@gmail.com
License: UNKNOWN
Platform: UNKNOWN
Classifier: Development Status :: 3 - Alpha
Classifier: Programming Language :: Python :: 3
Classifier: License :: OSI Approved :: MIT License
Classifier: Operating System :: OS Independent
Classifier: Environment :: Console
Classifier: Topic :: Text Processing :: Markup :: LaTeX
Requires-Python: >=3.6
